paramsx/__init__.py
paramsx/funcions.py
paramsx/main.py
paramsx/paramsx_config.py
paramsx/text.py
paramsx-1.1.5.dist-info/licenses/LICENSE
paramsx-1.1.5.dist-info/METADATA
paramsx-1.1.5.dist-info/WHEEL
paramsx-1.1.5.dist-info/entry_points.txt
paramsx-1.1.5.dist-info/top_level.txt
paramsx-1.1.5.dist-info/RECORD
