Metadata-Version: 2.4
Name: paramsx
Version: 1.1.5
Summary: Librería para gestionar y respaldar parámetros de AWS SSM de manera sencilla y eficiente.
Home-page: https://github.com/pistatxos/paramsx
Author: Mariox
Author-email: info@tomonota.net
License-File: LICENSE
Requires-Dist: boto3
Requires-Dist: windows-curses; platform_system == "Windows"
Dynamic: author
Dynamic: author-email
Dynamic: description
Dynamic: description-content-type
Dynamic: home-page
Dynamic: license-file
Dynamic: requires-dist
Dynamic: summary
